pytest_instafail.py
pytest_instafail-0.5.0.dist-info/LICENSE
pytest_instafail-0.5.0.dist-info/METADATA
pytest_instafail-0.5.0.dist-info/WHEEL
pytest_instafail-0.5.0.dist-info/entry_points.txt
pytest_instafail-0.5.0.dist-info/top_level.txt
pytest_instafail-0.5.0.dist-info/RECORD
